rfhub2/__init__.py
rfhub2/__main__.py
rfhub2/alembic.ini
rfhub2/app.py
rfhub2/config.py
rfhub2/main.py
rfhub2/version.py
rfhub2/alembic/env.py
rfhub2/alembic/versions/abee96e78502_add_tags_to_keyword.py
rfhub2/alembic/versions/c54a916ec6c8_initial_model.py
rfhub2/alembic/versions/d3ab100869e0_add_suite_model.py
rfhub2/api/__init__.py
rfhub2/api/router.py
rfhub2/api/endpoints/__init__.py
rfhub2/api/endpoints/collections.py
rfhub2/api/endpoints/healthcheck.py
rfhub2/api/endpoints/keyword_statistics.py
rfhub2/api/endpoints/keywords.py
rfhub2/api/endpoints/version.py
rfhub2/api/middleware/__init__.py
rfhub2/api/middleware/db_session_middleware.py
rfhub2/api/utils/__init__.py
rfhub2/api/utils/auth.py
rfhub2/api/utils/db.py
rfhub2/api/utils/http.py
rfhub2/api/utils/order.py
rfhub2/cli/__init__.py
rfhub2/cli/__main__.py
rfhub2/cli/api_client.py
rfhub2/cli/cli.py
rfhub2/cli/keywords/__init__.py
rfhub2/cli/keywords/keywords_extractor.py
rfhub2/cli/keywords/keywords_importer.py
rfhub2/cli/statistics/__init__.py
rfhub2/cli/statistics/statistics_extractor.py
rfhub2/cli/statistics/statistics_importer.py
rfhub2/db/__init__.py
rfhub2/db/base.py
rfhub2/db/migrate.py
rfhub2/db/session.py
rfhub2/db/model/__init__.py
rfhub2/db/model/base_class.py
rfhub2/db/model/collection.py
rfhub2/db/model/keyword.py
rfhub2/db/model/keyword_statistics.py
rfhub2/db/model/mixins.py
rfhub2/db/model/suite.py
rfhub2/db/model/suite_rel.py
rfhub2/db/model/test_case.py
rfhub2/db/repository/__init__.py
rfhub2/db/repository/base_repository.py
rfhub2/db/repository/collection_repository.py
rfhub2/db/repository/keyword_repository.py
rfhub2/db/repository/keyword_statistics_repository.py
rfhub2/db/repository/ordering.py
rfhub2/db/repository/query_utils.py
rfhub2/db/repository/suite_repository.py
rfhub2/db/repository/test_case_repository.py
rfhub2/model/__init__.py
rfhub2/static/.gitignore
rfhub2/static/asset-manifest.json
rfhub2/static/favicon.ico
rfhub2/static/manifest.json
rfhub2-0.31.dist-info/LICENSE
rfhub2-0.31.dist-info/LICENSE.rst
rfhub2-0.31.dist-info/METADATA
rfhub2-0.31.dist-info/WHEEL
rfhub2-0.31.dist-info/entry_points.txt
rfhub2-0.31.dist-info/top_level.txt
rfhub2-0.31.dist-info/zip-safe
rfhub2-0.31.dist-info/RECORD
