Metadata-Version: 2.1
Name: rfhub2
Version: 0.31
Summary: Webserver for robot framework and python assets documentation
Home-page: https://github.com/pbylicki/rfhub2/
Author: Pawel Bylicki, Maciej Wiczk
Author-email: pawelkbylicki@gmail.com, maciejwiczk@gmail.com
License: Apache License 2.0
Keywords: robotframework
Classifier: Development Status :: 4 - Beta
Classifier: License :: OSI Approved :: Apache Software License
Classifier: Operating System :: Unix
Classifier: Framework :: Robot Framework
Classifier: Framework :: Robot Framework :: Tool
Classifier: Programming Language :: Python
Classifier: Programming Language :: Python :: 3.6
Classifier: Programming Language :: Python :: 3.7
Classifier: Programming Language :: Python :: 3.8
Classifier: Topic :: Software Development :: Testing
Classifier: Topic :: Software Development :: Quality Assurance
Classifier: Intended Audience :: Developers
License-File: LICENSE
License-File: LICENSE.rst
Requires-Dist: alembic (>=1.2.0)
Requires-Dist: aiofiles (>=0.4.0)
Requires-Dist: Click (>=7.0)
Requires-Dist: fastapi (>=0.46.0)
Requires-Dist: pydantic (<2.0,>=1.0)
Requires-Dist: robotframework (>=3.0.0)
Requires-Dist: SQLAlchemy (>=1.2.0)
Requires-Dist: requests (>=2.10.0)
Requires-Dist: uvicorn (>=0.7.1)
Requires-Dist: progress (>=1.4)
Provides-Extra: postgresql
Requires-Dist: psycopg2-binary (>=2.7.4) ; extra == 'postgresql'
